4-27/cpu.v
module CPU(CK,RST,IA,ID,DA,DD,RW);
   input CK,RST;
   input [15:0] ID;
   output RW;
   output [15:0] IA,DA;
   inout [15:0] DD;//Data 
   reg [15:0] PC, INST, FUA,
        FUB, LSUA, LSUB, FUC, LSUC, PCC, PCI;
   reg [15:0] RF[0:14];
   reg [1:0] STAGE;
   reg FLAG,RW;
   wire [15:0] ABUS, BBUS, CBUS;
   wire [3:0] OPCODE, OPR1,
         OPR2, OPR3;
   wire [7:0] IMM;
   wire [15:0] PCn;
   assign PCn = PC + 1;

	wire [15:0] RF01, RF05;
	assign RF01 = RF[1];
	assign RF05 = RF[5];


   assign OPCODE = INST[15:12];
   assign OPR1 = INST[11:8];
   assign OPR2 = INST[7:4];
   assign OPR3 = INST[3:0];
   assign IMM = INST[7:0];
   assign ABUS = (OPR2 == 0 ? 0 : RF[OPR2]);
   assign BBUS = (OPR3 == 0 ? 0 : RF[OPR3]);
   assign DA = LSUB;
   assign IA = PC;
   assign DD =((RW==0)? LSUA : 16'b Z);
   assign CBUS = (OPCODE[3]==0 ? FUC : (OPCODE[3:1]=='b 101 ? LSUC :
	(OPCODE=='b 1100 ? {8'b 0,IMM} : OPCODE=='b 1000 ? PCC : 'b z)));

always @(posedge CK) begin
	 if( RST == 1 ) begin   //reset
		PC <= 0;
		STAGE <= 0;
		RW<=1;
	end else if( STAGE == 0 ) begin
		INST <= ID;
		STAGE <= 1;
	end else if( STAGE == 1 ) begin
		if( (OPCODE[3:0] == 'b 1000) || (OPCODE[3:0] == 'b 1001 && FLAG == 1 ) ) PCI <= BBUS;
		else PCI <= PCn;

		if( OPCODE[3] == 0 ) begin
			FUA <= ABUS; FUB <= BBUS;
		end else if( OPCODE[2:1] == 'b01) begin
			LSUA <= ABUS; LSUB <= BBUS;
		end
		STAGE <= 2;
	end else if( STAGE == 2 ) begin
		if( OPCODE[3] == 0 ) begin
			case(OPCODE[2:0])
				'b 000: FUC<=FUA+FUB;
				'b 001: FUC<=FUA-FUB;
				'b 010: FUC<=FUA>>FUB;
				'b 011: FUC<=FUA<<FUB;
				'b 100: FUC<=FUA|FUB;
				'b 101: FUC<=FUA&FUB;
				'b 110: FUC<=~FUA;
				'b 111: FUC<=FUA^FUB;
			endcase
		end else if( OPCODE[3:1] == 'b 101 ) begin
			if( OPCODE[0] == 0 ) begin
				RW <= 0;
			end else begin
				RW <= 1;
				LSUC <= DD;
			end
		end else if( OPCODE[3:0] == 'b 1000 ) PCC <= PC+1;
		STAGE <= 3;
	end else if( STAGE == 3 ) begin
	   RW <= 1;
	   if( OPCODE[3] == 0 ) begin
	      if( CBUS == 0 ) FLAG <= 1;
	      else FLAG <= 0;
	   end
	   
		RF[OPR1] <= CBUS;
		PC <= PCI;
		STAGE <= 0;
	end
end

endmodule

4-27/simcpu2.v
module simcpu;
reg CK, RST;
wire RW;
wire [15:0] IA, DA, DD;
reg [15:0] ID, DDi;
reg [15:0] IMEM [0:127], DMEM[0:127];

	CPU c(CK,RST,IA,ID,DA,DD,RW);

   assign DD = ((RW == 1) ? DDi : 'b Z);

initial begin
	//$dumpfile("cpu.vcd");
	//$dumpvars;
	CK = 0;
	RST = 0;
#5	RST = 1;
#100	RST = 0;
	
        #10000 $finish;
end

always @(negedge CK) begin
   if( DA == 'b 0 && DD == 'b 0100 && RW == 0 ) begin
      $display( "OK" );
      $finish;
   end
end

always @(negedge CK) begin
	ID = IMEM[IA];
end

always @(negedge CK) begin
   if( RW == 1 ) DDi = DMEM[DA];
   else DMEM[DA] = DD;
end

initial begin
   IMEM[0]=	'b 1100_0000_0000_0000;	// IMM  R0, [0]
   IMEM[1]=	'b 1100_0001_0000_0001; // IMM  R1, [1]
   IMEM[2]=	'b 1100_0010_0000_0010; // IMM  R2, [2]
   IMEM[3]=	'b 1100_0011_0000_0011; // IMM  R3, [3]
   IMEM[4]=	'b 1100_0100_0000_0100; // IMM  R4, [4]
   IMEM[5]=	'b 0000_0101_0001_0011; // ADD  R5, R1, R3
   IMEM[6]=	'b 1010_0000_0101_0000; // ST  R5, R0
end

always #10 CK = ~CK;

endmodule

4-27/cpu.vcd
$date
	Fri Apr 27 11:38:08 2018
$end
$version
	Icarus Verilog
$end
$timescale
	1s
$end
$scope module simcpu $end
$var wire 16 ! DA [15:0] $end
$var wire 16 " DD [15:0] $end
$var wire 16 # IA [15:0] $end
$var wire 1 $ RW $end
$var reg 1 % CK $end
$var reg 16 & DDi [15:0] $end
$var reg 16 ' ID [15:0] $end
$var reg 1 ( RST $end
$scope module c $end
$var wire 16 ) ABUS [15:0] $end
$var wire 16 * BBUS [15:0] $end
$var wire 16 + CBUS [15:0] $end
$var wire 1 , CK $end
$var wire 16 - DA [15:0] $end
$var wire 16 . DD [15:0] $end
$var wire 16 / IA [15:0] $end
$var wire 16 0 ID [15:0] $end
$var wire 8 1 IMM [7:0] $end
$var wire 4 2 OPCODE [3:0] $end
$var wire 4 3 OPR1 [3:0] $end
$var wire 4 4 OPR2 [3:0] $end
$var wire 4 5 OPR3 [3:0] $end
$var wire 16 6 PCn [15:0] $end
$var wire 16 7 RF01 [15:0] $end
$var wire 16 8 RF05 [15:0] $end
$var wire 1 9 RST $end
$var reg 1 : FLAG $end
$var reg 16 ; FUA [15:0] $end
$var reg 16 < FUB [15:0] $end
$var reg 16 = FUC [15:0] $end
$var reg 16 > INST [15:0] $end
$var reg 16 ? LSUA [15:0] $end
$var reg 16 @ LSUB [15:0] $end
$var reg 16 A LSUC [15:0] $end
$var reg 16 B PC [15:0] $end
$var reg 16 C PCC [15:0] $end
$var reg 16 D PCI [15:0] $end
$var reg 1 E RW $end
$var reg 2 F STAGE [1:0] $end
$upscope $end
$upscope $end
$enddefinitions $end
#0
$dumpvars
bx F
xE
bx D
bx C
bx B
bx A
bx @
bx ?
bx >
bx =
bx <
bx ;
x:
09
bz 8
bz 7
bx 6
bx 5
bx 4
bx 3
bx 2
bx 1
bx 0
bx /
bx .
bx -
0,
bx +
bx *
bx )
0(
bx '
bx &
0%
x$
bx #
bx "
bx !
$end
#5
1(
19
#10
b1 6
1E
1$
b0 F
b0 B
b0 #
b0 /
1%
1,
#20
b1100000000000000 '
b1100000000000000 0
0%
0,
#30
1%
1,
#40
0%
0,
#50
1%
1,
#60
0%
0,
#70
1%
1,
#80
0%
0,
#90
1%
1,
#100
0%
0,
#105
0(
09
#110
b0 +
b0 )
b0 *
b1100 2
b0 3
b0 4
b0 5
b0 1
b1 F
b1100000000000000 >
1%
1,
#120
0%
0,
#130
b10 F
b1 D
1%
1,
#140
0%
0,
#150
b11 F
1%
1,
#160
0%
0,
#170
b10 6
b0 F
b1 B
b1 #
b1 /
1%
1,
#180
b1100000100000001 '
b1100000100000001 0
0%
0,
#190
b1 +
bx *
b1 3
b1 5
b1 1
b1 F
b1100000100000001 >
1%
1,
#200
0%
0,
#210
b10 F
b10 D
1%
1,
#220
0%
0,
#230
b11 F
1%
1,
#240
0%
0,
#250
b11 6
b1 *
b0 F
b10 B
b10 #
b10 /
b1 7
1%
1,
#260
b1100001000000010 '
b1100001000000010 0
0%
0,
#270
b10 +
bx *
b10 3
b10 5
b10 1
b1 F
b1100001000000010 >
1%
1,
#280
0%
0,
#290
b10 F
b11 D
1%
1,
#300
0%
0,
#310
b11 F
1%
1,
#320
0%
0,
#330
b100 6
b10 *
b0 F
b11 B
b11 #
b11 /
1%
1,
#340
b1100001100000011 '
b1100001100000011 0
0%
0,
#350
b11 +
bx *
b11 3
b11 5
b11 1
b1 F
b1100001100000011 >
1%
1,
#360
0%
0,
#370
b10 F
b100 D
1%
1,
#380
0%
0,
#390
b11 F
1%
1,
#400
0%
0,
#410
b101 6
b11 *
b0 F
b100 B
b100 #
b100 /
1%
1,
#420
b1100010000000100 '
b1100010000000100 0
0%
0,
#430
b100 +
bx *
b100 3
b100 5
b100 1
b1 F
b1100010000000100 >
1%
1,
#440
0%
0,
#450
b10 F
b101 D
1%
1,
#460
0%
0,
#470
b11 F
1%
1,
#480
0%
0,
#490
b110 6
b100 *
b0 F
b101 B
b101 #
b101 /
1%
1,
#500
b10100010011 '
b10100010011 0
0%
0,
#510
bx +
b1 )
b11 *
b0 2
b101 3
b1 4
b11 5
b10011 1
b1 F
b10100010011 >
1%
1,
#520
0%
0,
#530
b10 F
b11 <
b1 ;
b110 D
1%
1,
#540
0%
0,
#550
b100 +
b11 F
b100 =
1%
1,
#560
0%
0,
#570
b111 6
b0 F
b110 B
b110 #
b110 /
b100 8
0:
1%
1,
#580
b1010000001010000 '
b1010000001010000 0
0%
0,
#590
bx +
b100 )
b0 *
b1010 2
b0 3
b101 4
b0 5
b1010000 1
b1 F
b1010000001010000 >
1%
1,
#600
0%
0,
#610
b10 F
b0 @
b0 !
b0 -
b100 ?
b111 D
1%
1,
#620
0%
0,
#630
b100 "
b100 .
b11 F
0E
0$
1%
1,
